DozDetPazuihouyici/__init__.py
DozDetPazuihouyici/main.py
DozDetPazuihouyici/timer.py
DozDetPazuihouyici-0.1.0.dist-info/LICENCE.txt
DozDetPazuihouyici-0.1.0.dist-info/METADATA
DozDetPazuihouyici-0.1.0.dist-info/WHEEL
DozDetPazuihouyici-0.1.0.dist-info/entry_points.txt
DozDetPazuihouyici-0.1.0.dist-info/top_level.txt
DozDetPazuihouyici-0.1.0.dist-info/RECORD
